SNUPEL/__init__.py
SNUPEL/SimEnv/__init__.py
SNUPEL/SimEnv/FJSP/__init__.py
SNUPEL/SimEnv/FJSP/cfg_local.py
SNUPEL/SimEnv/FJSP/environment/Monitor.py
SNUPEL/SimEnv/FJSP/environment/Part.py
SNUPEL/SimEnv/FJSP/environment/Process.py
SNUPEL/SimEnv/FJSP/environment/Resource.py
SNUPEL/SimEnv/FJSP/environment/Sink.py
SNUPEL/SimEnv/FJSP/environment/Source.py
SNUPEL/SimEnv/FJSP/environment/__init__.py
SNUPEL/SimEnv/FJSP/environment/연습.py
SNUPEL/SimEnv/FJSP/postprocessing/PostProcessing.py
SNUPEL/SimEnv/FJSP/postprocessing/__init__.py
SNUPEL/SimEnv/FJSP/test_abz5/__init__.py
SNUPEL/SimEnv/FJSP/test_abz5/data.py
SNUPEL/SimEnv/FJSP/test_abz5/test_abz5.py
SNUPEL/SimEnv/FJSP/test_fjsp/__init__.py
SNUPEL/SimEnv/FJSP/test_fjsp/data_FJSP.py
SNUPEL/SimEnv/FJSP/test_ft06/__init__.py
SNUPEL/SimEnv/FJSP/test_ft06/test_ft06.py
SNUPEL/SimEnv/FJSP/test_general/__init__.py
SNUPEL/SimEnv/FJSP/test_general/test_general.py
SNUPEL/SimEnv/FJSP/test_quay/__init__.py
SNUPEL/SimEnv/FJSP/test_quay/data_quay.py
SNUPEL/SimEnv/FJSP/test_quay/test_quay.py
SNUPEL/SimEnv/FJSP/visualization/GUI.py
SNUPEL/SimEnv/FJSP/visualization/Gantt.py
SNUPEL/SimEnv/FJSP/visualization/__init__.py
SNUPEL/SimEnv/IPMSP/__init__.py
SNUPEL/SimEnv/IPMSP/env.py
SNUPEL/SimEnv/IPMSP/simulation.py
SNUPEL/SimEnv/JSSP/__init__.py
SNUPEL/SimEnv/JSSP/main.py
SNUPEL/SimEnv/JSSP/utils.py
SNUPEL/SimEnv/JSSP/Config/Run_Config.py
SNUPEL/SimEnv/JSSP/Config/__init__.py
SNUPEL/SimEnv/JSSP/Data/DataGenerator.py
SNUPEL/SimEnv/JSSP/Data/__init__.py
SNUPEL/SimEnv/JSSP/Data/statistics.py
SNUPEL/SimEnv/JSSP/Data/Adams/__init__.py
SNUPEL/SimEnv/JSSP/Data/Adams/abz5/__init__.py
SNUPEL/SimEnv/JSSP/Data/Adams/abz5/abz5.py
SNUPEL/SimEnv/JSSP/Data/Adams/abz6/__init__.py
SNUPEL/SimEnv/JSSP/Data/Adams/abz6/abz6.py
SNUPEL/SimEnv/JSSP/Data/Adams/abz7/__init__.py
SNUPEL/SimEnv/JSSP/Data/Adams/abz7/abz7.py
SNUPEL/SimEnv/JSSP/Data/Adams/abz7/abz7_test.py
SNUPEL/SimEnv/JSSP/Data/Adams/abz8/__init__.py
SNUPEL/SimEnv/JSSP/Data/Adams/abz8/abz8.py
snupel_modules-0.0.2.dist-info/LICENSE.md
snupel_modules-0.0.2.dist-info/METADATA
snupel_modules-0.0.2.dist-info/WHEEL
snupel_modules-0.0.2.dist-info/top_level.txt
snupel_modules-0.0.2.dist-info/RECORD
