Metadata-Version: 2.1
Name: snupel-modules
Version: 0.0.2
Summary: Seoul National University Production Engineering Laboratory Machine Learning Simulation Modules
Home-page: https://github.com/pypa/sampleproject
Author: WonSeok Choi
Author-email: wschoi0312@snu.ac.kr
Classifier: Programming Language :: Python :: 3
Classifier: License :: OSI Approved :: MIT License
Classifier: Operating System :: OS Independent
Requires-Python: >=3.6
License-File: LICENSE.md
